TheNounProjectAPI/__init__.py
TheNounProjectAPI/__version__.py
TheNounProjectAPI/api.py
TheNounProjectAPI/api_test.py
TheNounProjectAPI/call.py
TheNounProjectAPI/collections.py
TheNounProjectAPI/context.py
TheNounProjectAPI/core.py
TheNounProjectAPI/enterprise.py
TheNounProjectAPI/exceptions.py
TheNounProjectAPI/icons.py
TheNounProjectAPI/keys.py
TheNounProjectAPI/models.py
TheNounProjectAPI/usage.py
TheNounProjectAPI-1.0.5.dist-info/LICENSE
TheNounProjectAPI-1.0.5.dist-info/METADATA
TheNounProjectAPI-1.0.5.dist-info/WHEEL
TheNounProjectAPI-1.0.5.dist-info/top_level.txt
TheNounProjectAPI-1.0.5.dist-info/RECORD
