Metadata-Version: 2.1
Name: TheNounProjectAPI
Version: 1.0.5
Summary: Python The Noun Project API Wrapper.
Home-page: https://github.com/CubieDev/TheNounProjectAPI
Author: Tom Aarsen
Author-email: cubiegamedev@gmail.com
License: MIT
Platform: UNKNOWN
Classifier: License :: OSI Approved :: MIT License
Classifier: Programming Language :: Python
Classifier: Programming Language :: Python :: 3
Classifier: Programming Language :: Python :: 3.7
Classifier: Programming Language :: Python :: Implementation :: CPython
Classifier: Programming Language :: Python :: Implementation :: PyPy
Requires-Python: >=3.7.0
Requires-Dist: requests
Requires-Dist: requests-oauthlib
Requires-Dist: wrapt
